{
    "leagues": [
      {
        "id": 1,
        "name": "Premier League",
        "image": "/assets/prem.jpg",
        "teams": [
        {
            "id": 101,
            "name": "Manchester City",
            "image": "la_liga.png",
            "players": [
            { "id": 1001, "name": "Kevin De Bruyne", "position": "Midfielder" },
            { "id": 1002, "name": "Erling Haaland", "position": "Forward" },
            { "id": 1003, "name": "Phil Foden", "position": "Midfielder" },
            { "id": 1004, "name": "Ruben Dias", "position": "Defender" },
            { "id": 1005, "name": "Rodri", "position": "Midfielder" },
            { "id": 1006, "name": "Jack Grealish", "position": "Forward" },
            { "id": 1007, "name": "Ederson", "position": "Goalkeeper" },
            { "id": 1008, "name": "Bernardo Silva", "position": "Midfielder" },
            { "id": 1009, "name": "Joao Cancelo", "position": "Defender" },
            { "id": 1010, "name": "John Stones", "position": "Defender" },
            { "id": 1011, "name": "Kyle Walker", "position": "Defender" }
            ]
        },
        {
            "id": 102,
            "name": "Liverpool",
            "image": "la_liga.png",
            "players": [
            { "id": 1101, "name": "Mohamed Salah", "position": "Forward" },
            { "id": 1102, "name": "Virgil van Dijk", "position": "Defender" },
            { "id": 1103, "name": "Alisson Becker", "position": "Goalkeeper" },
            { "id": 1104, "name": "Trent Alexander-Arnold", "position": "Defender" },
            { "id": 1105, "name": "Andrew Robertson", "position": "Defender" },
            { "id": 1106, "name": "Fabinho", "position": "Midfielder" },
            { "id": 1107, "name": "Diogo Jota", "position": "Forward" },
            { "id": 1108, "name": "Jordan Henderson", "position": "Midfielder" },
            { "id": 1109, "name": "Darwin Núñez", "position": "Forward" },
            { "id": 1110, "name": "Luis Díaz", "position": "Forward" },
            { "id": 1111, "name": "Ibrahima Konaté", "position": "Defender" }
            ]
        },
        {
            "id": 103,
            "name": "Chelsea",
            "image": "la_liga.png",
            "players": [
            { "id": 1201, "name": "Kai Havertz", "position": "Forward" },
            { "id": 1202, "name": "Mason Mount", "position": "Midfielder" },
            { "id": 1203, "name": "N'Golo Kanté", "position": "Midfielder" },
            { "id": 1204, "name": "Thiago Silva", "position": "Defender" },
            { "id": 1205, "name": "Raheem Sterling", "position": "Forward" },
            { "id": 1206, "name": "Ben Chilwell", "position": "Defender" },
            { "id": 1207, "name": "Edouard Mendy", "position": "Goalkeeper" },
            { "id": 1208, "name": "Jorginho", "position": "Midfielder" },
            { "id": 1209, "name": "Christian Pulisic", "position": "Forward" },
            { "id": 1210, "name": "César Azpilicueta", "position": "Defender" },
            { "id": 1211, "name": "Ruben Loftus-Cheek", "position": "Midfielder" }
            ]
        },
        {
            "id": 104,
            "name": "Manchester United",
            "image": "la_liga.png",
            "players": [
            { "id": 1301, "name": "Bruno Fernandes", "position": "Midfielder" },
            { "id": 1302, "name": "Cristiano Ronaldo", "position": "Forward" },
            { "id": 1303, "name": "David de Gea", "position": "Goalkeeper" },
            { "id": 1304, "name": "Raphaël Varane", "position": "Defender" },
            { "id": 1305, "name": "Marcus Rashford", "position": "Forward" },
            { "id": 1306, "name": "Paul Pogba", "position": "Midfielder" },
            { "id": 1307, "name": "Luke Shaw", "position": "Defender" },
            { "id": 1308, "name": "Jadon Sancho", "position": "Forward" },
            { "id": 1309, "name": "Harry Maguire", "position": "Defender" },
            { "id": 1310, "name": "Aaron Wan-Bissaka", "position": "Defender" },
            { "id": 1311, "name": "Fred", "position": "Midfielder" }
            ]
        },
        {
            "id": 105,
            "name": "Arsenal",
            "image": "la_liga.png",
            "players": [
            { "id": 1401, "name": "Bukayo Saka", "position": "Forward" },
            { "id": 1402, "name": "Martin Ødegaard", "position": "Midfielder" },
            { "id": 1403, "name": "Aaron Ramsdale", "position": "Goalkeeper" },
            { "id": 1404, "name": "Gabriel Magalhães", "position": "Defender" },
            { "id": 1405, "name": "Thomas Partey", "position": "Midfielder" },
            { "id": 1406, "name": "Alexander Lacazette", "position": "Forward" },
            { "id": 1407, "name": "Ben White", "position": "Defender" },
            { "id": 1408, "name": "Kieran Tierney", "position": "Defender" },
            { "id": 1409, "name": "Gabriel Martinelli", "position": "Forward" },
            { "id": 1410, "name": "Martinelli", "position": "Forward" },
            { "id": 1411, "name": "Emile Smith Rowe", "position": "Midfielder" }
            ]
        }
    ]
      },
      {
        "id": 2,
        "name": "La Liga",
        "image": "la_liga.png",
        "teams": [
    {
      "id": 201,
      "name": "Real Madrid",
      "image": "realmadrid.png",
      "players": [
        { "id": 2001, "name": "Vinicius Jr.", "position": "Forward" },
        { "id": 2002, "name": "Luka Modric", "position": "Midfielder" },
        { "id": 2003, "name": "Karim Benzema", "position": "Forward" },
        { "id": 2004, "name": "Thibaut Courtois", "position": "Goalkeeper" },
        { "id": 2005, "name": "Toni Kroos", "position": "Midfielder" },
        { "id": 2006, "name": "Eduardo Camavinga", "position": "Midfielder" },
        { "id": 2007, "name": "David Alaba", "position": "Defender" },
        { "id": 2008, "name": "Éder Militão", "position": "Defender" },
        { "id": 2009, "name": "Rodrygo", "position": "Forward" },
        { "id": 2010, "name": "Ferland Mendy", "position": "Defender" },
        { "id": 2011, "name": "Federico Valverde", "position": "Midfielder" }
      ]
    },
    {
      "id": 202,
      "name": "Barcelona",
      "image": "barcelona.png",
      "players": [
        { "id": 2101, "name": "Robert Lewandowski", "position": "Forward" },
        { "id": 2102, "name": "Sergio Busquets", "position": "Midfielder" },
        { "id": 2103, "name": "Marc-André ter Stegen", "position": "Goalkeeper" },
        { "id": 2104, "name": "Gerard Piqué", "position": "Defender" },
        { "id": 2105, "name": "Pierre-Emerick Aubameyang", "position": "Forward" },
        { "id": 2106, "name": "Frenkie de Jong", "position": "Midfielder" },
        { "id": 2107, "name": "Jordi Alba", "position": "Defender" },
        { "id": 2108, "name": "Ansu Fati", "position": "Forward" },
        { "id": 2109, "name": "Clement Lenglet", "position": "Defender" },
        { "id": 2110, "name": "Sergi Roberto", "position": "Midfielder" },
        { "id": 2111, "name": "Memphis Depay", "position": "Forward" }
      ]
    },
    {
      "id": 203,
      "name": "Atlético Madrid",
      "image": "atleticomadrid.png",
      "players": [
        { "id": 2201, "name": "Antoine Griezmann", "position": "Forward" },
        { "id": 2202, "name": "Jan Oblak", "position": "Goalkeeper" },
        { "id": 2203, "name": "João Félix", "position": "Forward" },
        { "id": 2204, "name": "Koke", "position": "Midfielder" },
        { "id": 2205, "name": "Saúl Ñíguez", "position": "Midfielder" },
        { "id": 2206, "name": "Luis Suárez", "position": "Forward" },
        { "id": 2207, "name": "Stefan Savić", "position": "Defender" },
        { "id": 2208, "name": "Mario Hermoso", "position": "Defender" },
        { "id": 2209, "name": "Ángel Correa", "position": "Forward" },
        { "id": 2210, "name": "Renan Lodi", "position": "Defender" },
        { "id": 2211, "name": "Yannick Carrasco", "position": "Forward" }
      ]
    },
    {
      "id": 204,
      "name": "Sevilla",
      "image": "sevilla.png",
      "players": [
        { "id": 2301, "name": "Youssef En-Nesyri", "position": "Forward" },
        { "id": 2302, "name": "Ivan Rakitic", "position": "Midfielder" },
        { "id": 2303, "name": "Bono", "position": "Goalkeeper" },
        { "id": 2304, "name": "Jules Koundé", "position": "Defender" },
        { "id": 2305, "name": "Suso", "position": "Forward" },
        { "id": 2306, "name": "Lucas Ocampos", "position": "Forward" },
        { "id": 2307, "name": "Fernando", "position": "Midfielder" },
        { "id": 2308, "name": "Diego Carlos", "position": "Defender" },
        { "id": 2309, "name": "Joan Jordán", "position": "Midfielder" },
        { "id": 2310, "name": "Munir El Haddadi", "position": "Forward" },
        { "id": 2311, "name": "Alejandro Gómez", "position": "Forward" }
      ]
    },
    {
      "id": 205,
      "name": "Real Sociedad",
      "image": "realsociedad.png",
      "players": [
        { "id": 2401, "name": "Mikel Oyarzabal", "position": "Forward" },
        { "id": 2402, "name": "David Silva", "position": "Midfielder" },
        { "id": 2403, "name": "Alex Remiro", "position": "Goalkeeper" },
        { "id": 2404, "name": "Aritz Elustondo", "position": "Defender" },
        { "id": 2405, "name": "Portu", "position": "Forward" },
        { "id": 2406, "name": "Martin Zubimendi", "position": "Midfielder" },
        { "id": 2407, "name": "Mikel Merino", "position": "Midfielder" },
        { "id": 2408, "name": "Willian José", "position": "Forward" },
        { "id": 2409, "name": "Carlos Fernández", "position": "Forward" },
        { "id": 2410, "name": "Jon Pacheco", "position": "Defender" },
        { "id": 2411, "name": "Igor Zubeldia", "position": "Midfielder" }
      ]
    }
  ]
      },
      {
        "id": 3,
        "name": "Serie A",
        "image": "SerieA.png",
        "teams": [
          {
            "id": 301,
            "name": "Juventus",
            "image": "juventus.png",
            "players": [
              { "id": 2301, "name": "Cristiano Ronaldo", "position": "Forward" },
              { "id": 2302, "name": "Paulo Dybala", "position": "Forward" },
              { "id": 2303, "name": "Gianluigi Buffon", "position": "Goalkeeper" },
              { "id": 2304, "name": "Leonardo Bonucci", "position": "Defender" },
              { "id": 2305, "name": "Federico Chiesa", "position": "Forward" },
              { "id": 2306, "name": "Arthur Melo", "position": "Midfielder" },
              { "id": 2307, "name": "Adrien Rabiot", "position": "Midfielder" },
              { "id": 2308, "name": "Danilo", "position": "Defender" },
              { "id": 2309, "name": "Dejan Kulusevski", "position": "Forward" },
              { "id": 2310, "name": "Matthijs de Ligt", "position": "Defender" },
              { "id": 2311, "name": "Juan Cuadrado", "position": "Midfielder" }
            ]
          },
          {
            "id": 302,
            "name": "AC Milan",
            "image": "acmilan.png",
            "players": [
              { "id": 2401, "name": "Zlatan Ibrahimović", "position": "Forward" },
              { "id": 2402, "name": "Stefano Pioli", "position": "Manager" },
              { "id": 2403, "name": "Theo Hernandez", "position": "Defender" },
              { "id": 2404, "name": "Gianluigi Donnarumma", "position": "Goalkeeper" },
              { "id": 2405, "name": "Ante Rebić", "position": "Forward" },
              { "id": 2406, "name": "Franck Kessié", "position": "Midfielder" },
              { "id": 2407, "name": "Ismaël Bennacer", "position": "Midfielder" },
              { "id": 2408, "name": "Alessio Romagnoli", "position": "Defender" },
              { "id": 2409, "name": "Rafael Leão", "position": "Forward" },
              { "id": 2410, "name": "Davide Calabria", "position": "Defender" },
              { "id": 2411, "name": "Sandro Tonali", "position": "Midfielder" }
            ]
          },
          {
            "id": 303,
            "name": "Inter Milan",
            "image": "intermilan.png",
            "players": [
              { "id": 2501, "name": "Romelu Lukaku", "position": "Forward" },
              { "id": 2502, "name": "Lautaro Martínez", "position": "Forward" },
              { "id": 2503, "name": "Samir Handanović", "position": "Goalkeeper" },
              { "id": 2504, "name": "Milan Škriniar", "position": "Defender" },
              { "id": 2505, "name": "Nicolo Barella", "position": "Midfielder" },
              { "id": 2506, "name": "Arturo Vidal", "position": "Midfielder" },
              { "id": 2507, "name": "Achraf Hakimi", "position": "Defender" },
              { "id": 2508, "name": "Stefan de Vrij", "position": "Defender" },
              { "id": 2509, "name": "Ivan Perišić", "position": "Forward" },
              { "id": 2510, "name": "Christian Eriksen", "position": "Midfielder" },
              { "id": 2511, "name": "Matías Vecino", "position": "Midfielder" }
            ]
          },
          {
            "id": 304,
            "name": "AS Roma",
            "image": "asroma.png",
            "players": [
              { "id": 2601, "name": "Henrikh Mkhitaryan", "position": "Midfielder" },
              { "id": 2602, "name": "Paulo Dybala", "position": "Forward" },
              { "id": 2603, "name": "Lorenzo Pellegrini", "position": "Midfielder" },
              { "id": 2604, "name": "Gianluca Mancini", "position": "Defender" },
              { "id": 2605, "name": "Tammy Abraham", "position": "Forward" },
              { "id": 2606, "name": "Nicolo Zaniolo", "position": "Forward" },
              { "id": 2607, "name": "Roger Ibañez", "position": "Defender" },
              { "id": 2608, "name": "Chris Smalling", "position": "Defender" },
              { "id": 2609, "name": "Rui Patrício", "position": "Goalkeeper" },
              { "id": 2610, "name": "Bryan Cristante", "position": "Midfielder" },
              { "id": 2611, "name": "Leonardo Spinazzola", "position": "Defender" }
            ]
          },
          {
            "id": 305,
            "name": "Napoli",
            "image": "napoli.png",
            "players": [
              { "id": 2701, "name": "Victor Osimhen", "position": "Forward" },
              { "id": 2702, "name": "Lorenzo Insigne", "position": "Forward" },
              { "id": 2703, "name": "Khvicha Kvaratskhelia", "position": "Forward" },
              { "id": 2704, "name": "Fabian Ruiz", "position": "Midfielder" },
              { "id": 2705, "name": "Alex Meret", "position": "Goalkeeper" },
              { "id": 2706, "name": "Piotr Zieliński", "position": "Midfielder" },
              { "id": 2707, "name": "Giovanni Di Lorenzo", "position": "Defender" },
              { "id": 2708, "name": "Kalidou Koulibaly", "position": "Defender" },
              { "id": 2709, "name": "David Ospina", "position": "Goalkeeper" },
              { "id": 2710, "name": "André-Frank Zambo Anguissa", "position": "Midfielder" },
              { "id": 2711, "name": "Mario Rui", "position": "Defender" }
            ]
          }
        ]
      },
      {
        "id": 4,
        "name": "Bundesliga",
        "image": "bundesliga.png",
        "teams": [
          {
            "id": 401,
            "name": "Bayern Munich",
            "image": "bayernmunich.png",
            "players": [
              { "id": 3101, "name": "Robert Lewandowski", "position": "Forward" },
              { "id": 3102, "name": "Thomas Müller", "position": "Midfielder" },
              { "id": 3103, "name": "Manuel Neuer", "position": "Goalkeeper" },
              { "id": 3104, "name": "Joshua Kimmich", "position": "Midfielder" },
              { "id": 3105, "name": "Serge Gnabry", "position": "Forward" },
              { "id": 3106, "name": "Leon Goretzka", "position": "Midfielder" },
              { "id": 3107, "name": "Benjamin Pavard", "position": "Defender" },
              { "id": 3108, "name": "David Alaba", "position": "Defender" },
              { "id": 3109, "name": "Alphonso Davies", "position": "Defender" },
              { "id": 3110, "name": "Kingsley Coman", "position": "Forward" },
              { "id": 3111, "name": "Niklas Süle", "position": "Defender" }
            ]
          },
          {
            "id": 402,
            "name": "Borussia Dortmund",
            "image": "borussiadortmund.png",
            "players": [
              { "id": 3201, "name": "Erling Haaland", "position": "Forward" },
              { "id": 3202, "name": "Marco Reus", "position": "Forward" },
              { "id": 3203, "name": "Mats Hummels", "position": "Defender" },
              { "id": 3204, "name": "Jude Bellingham", "position": "Midfielder" },
              { "id": 3205, "name": "Jadon Sancho", "position": "Forward" },
              { "id": 3206, "name": "Raphaël Guerreiro", "position": "Defender" },
              { "id": 3207, "name": "Emre Can", "position": "Midfielder" },
              { "id": 3208, "name": "Gregor Kobel", "position": "Goalkeeper" },
              { "id": 3209, "name": "Thorgan Hazard", "position": "Forward" },
              { "id": 3210, "name": "Axel Witsel", "position": "Midfielder" },
              { "id": 3211, "name": "Matin Ødegaard", "position": "Midfielder" }
            ]
          },
          {
            "id": 403,
            "name": "RB Leipzig",
            "image": "rbleipzig.png",
            "players": [
              { "id": 3301, "name": "Christopher Nkunku", "position": "Forward" },
              { "id": 3302, "name": "Emil Forsberg", "position": "Midfielder" },
              { "id": 3303, "name": "Peter Gulácsi", "position": "Goalkeeper" },
              { "id": 3304, "name": "José Ángel Esmorís Tasende", "position": "Defender" },
              { "id": 3305, "name": "Yussuf Poulsen", "position": "Forward" },
              { "id": 3306, "name": "Kevin Kampl", "position": "Midfielder" },
              { "id": 3307, "name": "Ibrahima Konaté", "position": "Defender" },
              { "id": 3308, "name": "Marcel Sabitzer", "position": "Midfielder" },
              { "id": 3309, "name": "Dayot Upamecano", "position": "Defender" },
              { "id": 3310, "name": "Justin Kluivert", "position": "Forward" },
              { "id": 3311, "name": "Willi Orbán", "position": "Defender" }
            ]
          },
          {
            "id": 404,
            "name": "Bayer Leverkusen",
            "image": "bayerleverkusen.png",
            "players": [
              { "id": 3401, "name": "Leon Bailey", "position": "Forward" },
              { "id": 3402, "name": "Patrik Schick", "position": "Forward" },
              { "id": 3403, "name": "Lukas Hradecky", "position": "Goalkeeper" },
              { "id": 3404, "name": "Charles Aránguiz", "position": "Midfielder" },
              { "id": 3405, "name": "Florian Wirtz", "position": "Midfielder" },
              { "id": 3406, "name": "Sven Bender", "position": "Defender" },
              { "id": 3407, "name": "Edgar Sevrin", "position": "Defender" },
              { "id": 3408, "name": "Jeremie Frimpong", "position": "Defender" },
              { "id": 3409, "name": "Kerem Demirbay", "position": "Midfielder" },
              { "id": 3410, "name": "Moussa Diaby", "position": "Forward" },
              { "id": 3411, "name": "Jonathan Tah", "position": "Defender" }
            ]
          },
          {
            "id": 405,
            "name": "Borussia Mönchengladbach",
            "image": "borussiamonchengladbach.png",
            "players": [
              { "id": 3501, "name": "Marcus Thuram", "position": "Forward" },
              { "id": 3502, "name": "Jonas Hofmann", "position": "Midfielder" },
              { "id": 3503, "name": "Yann Sommer", "position": "Goalkeeper" },
              { "id": 3504, "name": "Matthias Ginter", "position": "Defender" },
              { "id": 3505, "name": "Alassane Pléa", "position": "Forward" },
              { "id": 3506, "name": "Christoph Kramer", "position": "Midfielder" },
              { "id": 3507, "name": "Stefan Lainer", "position": "Defender" },
              { "id": 3508, "name": "Breel Embolo", "position": "Forward" },
              { "id": 3509, "name": "Denis Zakaria", "position": "Midfielder" },
              { "id": 3510, "name": "Florian Neuhaus", "position": "Midfielder" },
              { "id": 3511, "name": "Ramy Bensebaini", "position": "Defender" }
            ]
          }
        ]
      },
      {
        "id": 5,
        "name": "Ligue 1",
        "image": "ligue1.png",
        "teams": [
    {
      "id": 301,
      "name": "Paris Saint-Germain",
      "image": "psg.png",
      "players": [
        { "id": 3001, "name": "Kylian Mbappé", "position": "Forward" },
        { "id": 3002, "name": "Lionel Messi", "position": "Forward" },
        { "id": 3003, "name": "Neymar Jr.", "position": "Forward" },
        { "id": 3004, "name": "Marco Verratti", "position": "Midfielder" },
        { "id": 3005, "name": "Sergio Ramos", "position": "Defender" },
        { "id": 3006, "name": "Achraf Hakimi", "position": "Defender" },
        { "id": 3007, "name": "Gianluigi Donnarumma", "position": "Goalkeeper" },
        { "id": 3008, "name": "Ander Herrera", "position": "Midfielder" },
        { "id": 3009, "name": "Marquinhos", "position": "Defender" },
        { "id": 3010, "name": "Leandro Paredes", "position": "Midfielder" },
        { "id": 3011, "name": "Mauro Icardi", "position": "Forward" }
      ]
    },
    {
      "id": 302,
      "name": "Olympique Marseille",
      "image": "marseille.png",
      "players": [
        { "id": 3101, "name": "Dimitri Payet", "position": "Forward" },
        { "id": 3102, "name": "Arkadiusz Milik", "position": "Forward" },
        { "id": 3103, "name": "Steve Mandanda", "position": "Goalkeeper" },
        { "id": 3104, "name": "Boubacar Kamara", "position": "Midfielder" },
        { "id": 3105, "name": "Valère Germain", "position": "Forward" },
        { "id": 3106, "name": "Mattéo Guendouzi", "position": "Midfielder" },
        { "id": 3107, "name": "Leonardo Balerdi", "position": "Defender" },
        { "id": 3108, "name": "Pol Lirola", "position": "Defender" },
        { "id": 3109, "name": "Jordan Amavi", "position": "Defender" },
        { "id": 3110, "name": "Cengiz Ünder", "position": "Forward" },
        { "id": 3111, "name": "Gerson", "position": "Midfielder" }
      ]
    },
    {
      "id": 303,
      "name": "AS Monaco",
      "image": "monaco.png",
      "players": [
        { "id": 3201, "name": "Wissam Ben Yedder", "position": "Forward" },
        { "id": 3202, "name": "Kamil Glik", "position": "Defender" },
        { "id": 3203, "name": "Cesc Fàbregas", "position": "Midfielder" },
        { "id": 3204, "name": "Stevan Jovetić", "position": "Forward" },
        { "id": 3205, "name": "Monegasque Tchouaméni", "position": "Midfielder" },
        { "id": 3206, "name": "Benjamin Lecomte", "position": "Goalkeeper" },
        { "id": 3207, "name": "Gelson Martins", "position": "Forward" },
        { "id": 3208, "name": "Niko Kovac", "position": "Manager" },
        { "id": 3209, "name": "Alexander Nübel", "position": "Goalkeeper" },
        { "id": 3210, "name": "Ruben Aguilar", "position": "Defender" },
        { "id": 3211, "name": "Kevin Volland", "position": "Forward" }
      ]
    },
    {
      "id": 304,
      "name": "Lyon",
      "image": "lyon.png",
      "players": [
        { "id": 3301, "name": "Karl Toko Ekambi", "position": "Forward" },
        { "id": 3302, "name": "Houssem Aouar", "position": "Midfielder" },
        { "id": 3303, "name": "Anthony Lopes", "position": "Goalkeeper" },
        { "id": 3304, "name": "Tino Kadewere", "position": "Forward" },
        { "id": 3305, "name": "Jason Denayer", "position": "Defender" },
        { "id": 3306, "name": "Léo Dubois", "position": "Defender" },
        { "id": 3307, "name": "Maxwel Cornet", "position": "Forward" },
        { "id": 3308, "name": "Lucas Paquetá", "position": "Midfielder" },
        { "id": 3309, "name": "Moussa Dembélé", "position": "Forward" },
        { "id": 3310, "name": "Marcelo", "position": "Defender" },
        { "id": 3311, "name": "Bruno Guimarães", "position": "Midfielder" }
      ]
    },
    {
      "id": 305,
      "name": "Lille OSC",
      "image": "lille.png",
      "players": [
        { "id": 3401, "name": "Burak Yılmaz", "position": "Forward" },
        { "id": 3402, "name": "José Fonte", "position": "Defender" },
        { "id": 3403, "name": "Mike Maignan", "position": "Goalkeeper" },
        { "id": 3404, "name": "Jonathan David", "position": "Forward" },
        { "id": 3405, "name": "Yusuf Yazıcı", "position": "Midfielder" },
        { "id": 3406, "name": "Benjamin André", "position": "Midfielder" },
        { "id": 3407, "name": "Zeki Çelik", "position": "Defender" },
        { "id": 3408, "name": "Timothy Weah", "position": "Forward" },
        { "id": 3409, "name": "Jonathan Ikoné", "position": "Forward" },
        { "id": 3410, "name": "Renato Sanches", "position": "Midfielder" },
        { "id": 3411, "name": "Jonathan Bamba", "position": "Forward" }
      ]
    }
  ]
      }        
    ]
  }
  